mocr/__init__.py
mocr/browser/__init__.py
mocr/browser/browser.py
mocr/browser/console.py
mocr/browser/context.py
mocr/browser/page.py
mocr/browser/target.py
mocr/browser/viewport.py
mocr/browser/worker.py
mocr/connection/__init__.py
mocr/connection/base.py
mocr/connection/connection.py
mocr/connection/devtools.py
mocr/console.py
mocr/constants/__init__.py
mocr/constants/events.py
mocr/constants/http.py
mocr/constants/info.py
mocr/constants/javascript/__init__.py
mocr/constants/javascript/add_binding.js
mocr/constants/javascript/element_in_view.js
mocr/constants/javascript/embed_js.js
mocr/constants/javascript/embed_js_url.js
mocr/constants/javascript/embed_style.js
mocr/constants/javascript/embed_style_url.js
mocr/constants/javascript/evaluate_xpath.js
mocr/constants/javascript/fetch_request.js
mocr/constants/javascript/get_binding_result.js
mocr/constants/javascript/get_content.js
mocr/constants/javascript/get_property.js
mocr/constants/javascript/scroll_into_view.js
mocr/constants/javascript/select_values.js
mocr/constants/javascript/set_content.js
mocr/constants/javascript/wait_for_node.js
mocr/constants/javascript/wait_for_page.js
mocr/constants/keys.py
mocr/constants/typing.py
mocr/download.py
mocr/exceptions.py
mocr/execution/__init__.py
mocr/execution/context.py
mocr/execution/handle/__init__.py
mocr/execution/handle/element.py
mocr/execution/handle/javascript.py
mocr/frame/__init__.py
mocr/frame/frame.py
mocr/frame/manager.py
mocr/frame/wait.py
mocr/input/__init__.py
mocr/input/dialog.py
mocr/input/keyboard.py
mocr/input/mouse.py
mocr/input/touchscreen.py
mocr/launch/__init__.py
mocr/launch/base.py
mocr/launch/chromium.py
mocr/launch/firefox.py
mocr/network/__init__.py
mocr/network/event.py
mocr/network/extensions/ffauth/background.js
mocr/network/extensions/ffauth/manifest.json
mocr/network/fetch.py
mocr/network/http.py
mocr/network/manager/__init__.py
mocr/network/manager/base.py
mocr/network/manager/chromium.py
mocr/network/manager/firefox.py
mocr_auto-0.1.0.dist-info/LICENSE
mocr_auto-0.1.0.dist-info/METADATA
mocr_auto-0.1.0.dist-info/WHEEL
mocr_auto-0.1.0.dist-info/RECORD
