Metadata-Version: 2.1
Name: mocr-auto
Version: 0.1.0
Summary: Remote web browser automation.
Author: Michael Everingham
Author-email: 36551116+michaeleveringham@users.noreply.github.com
Requires-Python: >=3.9,<4.0
Classifier: Programming Language :: Python :: 3
Classifier: Programming Language :: Python :: 3.9
Classifier: Programming Language :: Python :: 3.10
Classifier: Programming Language :: Python :: 3.11
Classifier: Programming Language :: Python :: 3.12
Requires-Dist: geckordp (>=0.4.53,<0.5.0)
Requires-Dist: httpx[http2,socks] (>=0.27.0,<0.28.0)
Requires-Dist: pyee (>=11.1.0,<12.0.0)
Requires-Dist: requests (>=2.31.0,<3.0.0)
Requires-Dist: tqdm (>=4.66.2,<5.0.0)
Requires-Dist: websockets (>=12.0,<13.0)
